nefertem_profiling/__init__.py
nefertem_profiling/metadata/__init__.py
nefertem_profiling/metadata/report.py
nefertem_profiling/plugins/__init__.py
nefertem_profiling/plugins/builder.py
nefertem_profiling/plugins/plugin.py
nefertem_profiling/run/__init__.py
nefertem_profiling/run/run.py
nefertem_profiling-2.0.2.dist-info/LICENSE.txt
nefertem_profiling-2.0.2.dist-info/METADATA
nefertem_profiling-2.0.2.dist-info/WHEEL
nefertem_profiling-2.0.2.dist-info/top_level.txt
nefertem_profiling-2.0.2.dist-info/RECORD
